[
    {
        "Date": "10/10/2025",
        "Time": "",
        "Location": "825 Fraternity Rd",
        "Nature": "NON UCR REPORTABLE",
        "Case Number": "2510948",
        "Disposition": "CLOSED RPT FILED"
    },
    {
        "Date": "10/10/2025",
        "Time": "",
        "Location": "580 S 7TH ST",
        "Nature": "Traffic Offense",
        "Case Number": "2510955",
        "Disposition": "CLOSED RPT FILED"
    },
    {
        "Date": "10/10/2025",
        "Time": "",
        "Location": "79 STROHECKER FARM LN",
        "Nature": "Damaged Property, Private",
        "Case Number": "2510961",
        "Disposition": "CLOSED RPT FILED"
    },
    {
        "Date": "10/10/2025",
        "Time": "",
        "Location": "580 Snake Road",
        "Nature": "NON UCR REPORTABLE",
        "Case Number": "2510934",
        "Disposition": "CLOSED RPT FILED"
    },
    {
        "Date": "10/10/2025",
        "Time": "",
        "Location": "623 COLEMAN HALL DR",
        "Nature": "Theft Other",
        "Case Number": "2510967",
        "Disposition": "CLOSED RPT FILED"
    }
]