[
    {
        "Date": "10/04/2025",
        "Time": "",
        "Location": "ELAINE LANGONE CENTER,",
        "Nature": "Liquor, Other",
        "Case Number": "2510724",
        "Disposition": "JUDICIAL REFERRAL"
    },
    {
        "Date": "10/04/2025",
        "Time": "",
        "Location": "560 Pascucci Dr",
        "Nature": "NON UCR REPORTABLE",
        "Case Number": "2510702",
        "Disposition": "CLOSED RPT FILED"
    },
    {
        "Date": "10/04/2025",
        "Time": "",
        "Location": "754 Rotc Dr",
        "Nature": "Liquor, Possess",
        "Case Number": "2510717",
        "Disposition": "JUDICIAL REFERRAL"
    },
    {
        "Date": "10/04/2025",
        "Time": "",
        "Location": "51 STROHECKER FARM LN",
        "Nature": "Liquor, Possess",
        "Case Number": "2510722",
        "Disposition": "JUDICIAL REFERRAL"
    },
    {
        "Date": "10/04/2025",
        "Time": "",
        "Location": "560 S 7TH ST",
        "Nature": "Liquor, Possess",
        "Case Number": "2510726",
        "Disposition": "CLOSED RPT FILED"
    },
    {
        "Date": "10/04/2025",
        "Time": "",
        "Location": "198 BUCKNELL WEST DR",
        "Nature": "POLICE INFORMATION",
        "Case Number": "2510754",
        "Disposition": ""
    },
    {
        "Date": "10/04/2025",
        "Time": "",
        "Location": "570 LOOMIS ST",
        "Nature": "POLICE INFORMATION",
        "Case Number": "2510758",
        "Disposition": "CLOSED RPT FILED"
    },
    {
        "Date": "10/04/2025",
        "Time": "",
        "Location": "380 S 7TH ST",
        "Nature": "Liquor, Other",
        "Case Number": "2510753",
        "Disposition": "JUDICIAL REFERRAL"
    }
]